LICENSE
README.md
pyproject.toml
setup.py
cartoreader_lite/__init__.py
cartoreader_lite.egg-info/PKG-INFO
cartoreader_lite.egg-info/SOURCES.txt
cartoreader_lite.egg-info/dependency_links.txt
cartoreader_lite.egg-info/requires.txt
cartoreader_lite.egg-info/top_level.txt
cartoreader_lite/high_level/__init__.py
cartoreader_lite/high_level/study.py
cartoreader_lite/low_level/__init__.py
cartoreader_lite/low_level/read_mesh.py
cartoreader_lite/low_level/study.py
cartoreader_lite/low_level/utils.py
cartoreader_lite/low_level/visitags.py
cartoreader_lite/postprocessing/__init__.py
cartoreader_lite/postprocessing/geometry.py