Metadata-Version: 2.1
Name: cartoreader-lite
Version: 1.0.1
Summary: Cartoreader-lite provides a simplified and easy low-level access to CARTO3 studies.
Home-page: https://github.com/thomgrand/cartoreader-lite
Author: Thomas Grandits
Author-email: tomdev@gmx.net
License: AGPL
Platform: UNKNOWN
Classifier: Programming Language :: Python :: 3
Requires-Python: >=3.8
Provides-Extra: tests
Provides-Extra: docs
License-File: LICENSE
